streamsx/hdfs/__init__.py
streamsx/hdfs/_hdfs.py
streamsx.hdfs-1.5.9.dist-info/DESCRIPTION.rst
streamsx.hdfs-1.5.9.dist-info/LICENSE.txt
streamsx.hdfs-1.5.9.dist-info/METADATA
streamsx.hdfs-1.5.9.dist-info/RECORD
streamsx.hdfs-1.5.9.dist-info/WHEEL
streamsx.hdfs-1.5.9.dist-info/metadata.json
streamsx.hdfs-1.5.9.dist-info/top_level.txt
