Metadata-Version: 2.0
Name: streamsx.hdfs
Version: 1.5.9
Summary: HDFS integration for IBM Streams
Home-page: https://github.com/IBMStreams/streamsx.hdfs
Author: IBM Streams @ github.com
Author-email: hegermar@de.ibm.com
License: Apache License - Version 2.0
Keywords: streams,ibmstreams,streaming,analytics,streaming-analytics,hdfs
Platform: UNKNOWN
Classifier: Development Status :: 5 - Production/Stable
Classifier: License :: OSI Approved :: Apache Software License
Classifier: Programming Language :: Python :: 3
Classifier: Programming Language :: Python :: 3.5
Classifier: Programming Language :: Python :: 3.6
Classifier: Programming Language :: Python :: 3.7
Requires-Dist: streamsx
Requires-Dist: streamsx.toolkits
